README.md
setup.py
serving_agent/__init__.py
serving_agent/model_agent.py
serving_agent/web_agent.py
serving_agent.egg-info/PKG-INFO
serving_agent.egg-info/SOURCES.txt
serving_agent.egg-info/dependency_links.txt
serving_agent.egg-info/not-zip-safe
serving_agent.egg-info/requires.txt
serving_agent.egg-info/top_level.txt